[
    {
        "Id": 1,
        "Content": "鳴素異能"
    },
    {
        "Id": 2,
        "Content": "共鳴解放"
    },
    {
        "Id": 3,
        "Content": "共鳴エネルギー"
    },
    {
        "Id": 4,
        "Content": "固有スキル"
    },
    {
        "Id": 5,
        "Content": "連携スキル"
    },
    {
        "Id": 6,
        "Content": "落下攻撃"
    },
    {
        "Id": 7,
        "Content": "操作モジュール"
    },
    {
        "Id": 8,
        "Content": "落下傘モジュール"
    },
    {
        "Id": 9,
        "Content": "スキャン"
    },
    {
        "Id": 10,
        "Content": "係留"
    },
    {
        "Id": 11,
        "Content": "協奏エフェクト"
    },
    {
        "Id": 12,
        "Content": "重攻撃"
    },
    {
        "Id": 13,
        "Content": "空中回避"
    },
    {
        "Id": 14,
        "Content": "逆転反撃"
    },
    {
        "Id": 15,
        "Content": "補給箱"
    },
    {
        "Id": 16,
        "Content": "大事なアイテム"
    },
    {
        "Id": 17,
        "Content": "とんでもないなにか"
    },
    {
        "Id": 18,
        "Content": "素材"
    },
    {
        "Id": 19,
        "Content": "植物"
    },
    {
        "Id": 20,
        "Content": "ドア"
    },
    {
        "Id": 21,
        "Content": "重力ストリーミング"
    },
    {
        "Id": 22,
        "Content": "エレベーター"
    },
    {
        "Id": 23,
        "Content": "鳴域信号塔"
    },
    {
        "Id": 24,
        "Content": "隠し道"
    },
    {
        "Id": 25,
        "Content": "観光地"
    },
    {
        "Id": 26,
        "Content": "廃墟"
    },
    {
        "Id": 27,
        "Content": "仕掛け"
    },
    {
        "Id": 28,
        "Content": "幻像"
    },
    {
        "Id": 29,
        "Content": "異変生物"
    },
    {
        "Id": 30,
        "Content": "噓つき"
    },
    {
        "Id": 31,
        "Content": "追放者"
    },
    {
        "Id": 32,
        "Content": "変な人型生物"
    },
    {
        "Id": 33,
        "Content": "無音区"
    },
    {
        "Id": 34,
        "Content": "カラミティ級"
    },
    {
        "Id": 35,
        "Content": "ロード級"
    },
    {
        "Id": 36,
        "Content": "エリート級"
    },
    {
        "Id": 37,
        "Content": "ノーマル級"
    },
    {
        "Id": 38,
        "Content": "とりえのない下っ端"
    },
    {
        "Id": 39,
        "Content": "前"
    },
    {
        "Id": 40,
        "Content": "後"
    },
    {
        "Id": 41,
        "Content": "左"
    },
    {
        "Id": 42,
        "Content": "右"
    },
    {
        "Id": 43,
        "Content": "上"
    },
    {
        "Id": 44,
        "Content": "下"
    },
    {
        "Id": 45,
        "Content": "真ん中"
    },
    {
        "Id": 46,
        "Content": "東"
    },
    {
        "Id": 47,
        "Content": "南"
    },
    {
        "Id": 48,
        "Content": "西"
    },
    {
        "Id": 49,
        "Content": "北"
    },
    {
        "Id": 50,
        "Content": "東南"
    },
    {
        "Id": 51,
        "Content": "東北"
    },
    {
        "Id": 52,
        "Content": "西南"
    },
    {
        "Id": 53,
        "Content": "西北"
    },
    {
        "Id": 54,
        "Content": "裏"
    },
    {
        "Id": 55,
        "Content": "ジャンプ"
    },
    {
        "Id": 56,
        "Content": "ダッシュ"
    },
    {
        "Id": 57,
        "Content": "追跡"
    },
    {
        "Id": 58,
        "Content": "逃走"
    },
    {
        "Id": 59,
        "Content": "しゃがむ"
    },
    {
        "Id": 60,
        "Content": "歩く"
    },
    {
        "Id": 61,
        "Content": "滑空"
    },
    {
        "Id": 62,
        "Content": "倒す"
    },
    {
        "Id": 63,
        "Content": "片付ける"
    },
    {
        "Id": 64,
        "Content": "調理"
    },
    {
        "Id": 65,
        "Content": "商人"
    },
    {
        "Id": 66,
        "Content": "先駆条約"
    },
    {
        "Id": 67,
        "Content": "チチ物流"
    },
    {
        "Id": 68,
        "Content": "一休み"
    },
    {
        "Id": 69,
        "Content": "頑張れ"
    },
    {
        "Id": 70,
        "Content": "諦めるな"
    },
    {
        "Id": 71,
        "Content": "よく考えて"
    },
    {
        "Id": 72,
        "Content": "止るな"
    },
    {
        "Id": 73,
        "Content": "引き返せ"
    },
    {
        "Id": 74,
        "Content": "景色が良い"
    },
    {
        "Id": 75,
        "Content": "ヤバいかもしれない"
    },
    {
        "Id": 76,
        "Content": "避けろ"
    },
    {
        "Id": 77,
        "Content": "ここ"
    }
]