[
    {
        "Id": 1,
        "Content": "天城城区"
    },
    {
        "Id": 2,
        "Content": "中曲台地"
    },
    {
        "Id": 3,
        "Content": "云陵谷"
    },
    {
        "Id": 4,
        "Content": "无光之森"
    },
    {
        "Id": 5,
        "Content": "北落野"
    },
    {
        "Id": 6,
        "Content": "荒石高地"
    },
    {
        "Id": 7,
        "Content": "旧城遗址"
    },
    {
        "Id": 8,
        "Content": "遗落原乡"
    },
    {
        "Id": 9,
        "Content": "怨鸟泽"
    },
    {
        "Id": 10,
        "Content": "乘霄山"
    },
    {
        "Id": 11,
        "Content": "虎口山脉"
    },
    {
        "Id": 12,
        "Content": "黑海岸"
    },
    {
        "Id": 13,
        "Content": "皇龙"
    }
]