[
  {
    "Id": 1,
    "Content": "火が付いたまま……"
  },
  {
    "Id": 2,
    "Content": "火が付いたまま……"
  },
  {
    "Id": 3,
    "Content": "火が付いたまま……"
  },
  {
    "Id": 4,
    "Content": "火が付いたまま……"
  },
  {
    "Id": 5,
    "Content": "火が付いたまま……"
  },
  {
    "Id": 6,
    "Content": "火が付いたまま……"
  },
  {
    "Id": 7,
    "Content": "火が付いたまま……"
  },
  {
    "Id": 8,
    "Content": "火が付いたまま……"
  },
  {
    "Id": 9,
    "Content": "火が付いたまま……"
  },
  {
    "Id": 10,
    "Content": "これは、むかしむかしの物語。"
  },
  {
    "Id": 11,
    "Content": "「悲鳴」という災難が、この世界に深く根付けていた。"
  },
  {
    "Id": 12,
    "Content": "人類は絶望の中で言葉を失い、"
  },
  {
    "Id": 13,
    "Content": "そして沈黙の中で生まれ変わった。"
  },
  {
    "Id": 14,
    "Content": "それは、危険と希望が伴う新生。"
  },
  {
    "Id": 15,
    "Content": "大地が混沌なる者に蹂躙され、"
  },
  {
    "Id": 16,
    "Content": "人類は不穏と紛争の満ちた廃墟に立ち、光を求めた。"
  },
  {
    "Id": 17,
    "Content": "微光が黒い潮を切り裂き、"
  },
  {
    "Id": 18,
    "Content": "鳴動は命を結びつけた。"
  },
  {
    "Id": 19,
    "Content": "彼らは、遂に産まれた。"
  },
  {
    "Id": 20,
    "Content": "使命が与えられた「共鳴者」は、"
  },
  {
    "Id": 21,
    "Content": "儚い希望を手に握る。"
  },
  {
    "Id": 22,
    "Content": "彼らは長きにわたる曇りを払い、"
  },
  {
    "Id": 23,
    "Content": "その災難の温床を砕こうとしていた。"
  },
  {
    "Id": 24,
    "Content": "ただ、吹き荒れた冬風が、"
  },
  {
    "Id": 25,
    "Content": "彼らに勝利の賛歌を送った。"
  },
  {
    "Id": 26,
    "Content": "でも、破滅の火種はまた点けられ、"
  },
  {
    "Id": 27,
    "Content": "傷ついた大地の鳴き声が響く。"
  },
  {
    "Id": 28,
    "Content": "世界の裏に潜む暗流が、"
  },
  {
    "Id": 29,
    "Content": "新たな暴風を企んでいた。"
  },
  {
    "Id": 30,
    "Content": "霧に隠られた余燼が、"
  },
  {
    "Id": 31,
    "Content": "火が付いたまま……"
  },
  {
    "Id": 32,
    "Content": "気を付けて！"
  },
  {
    "Id": 33,
    "Content": "サイレントエリアが……甦っている！"
  },
  {
    "Id": 34,
    "Content": "俺の冠を……見なかった？"
  },
  {
    "Id": 35,
    "Content": "高レベルの混沌種？いいえ、違う……"
  },
  {
    "Id": 36,
    "Content": "絶対に……みんなが傷つきさせない！"
  },
  {
    "Id": 37,
    "Content": "秧、秧秧！あんた……"
  },
  {
    "Id": 38,
    "Content": "みんな……逃げ、て……"
  },
  {
    "Id": 39,
    "Content": "流れは……ここまで、かな……"
  },
  {
    "Id": 40,
    "Content": "秧……秧秧！"
  },
  {
    "Id": 41,
    "Content": "興が、冷めてきた。"
  },
  {
    "Id": 42,
    "Content": "安心しろ、そのうち何も感じられなくしてやる。"
  },
  {
    "Id": 43,
    "Content": "待ってよ！桃祈…勝手にこいつを置いていかないでよ！"
  },
  {
    "Id": 44,
    "Content": "はいはい……ついてこいよ。道を案内して差し上げますね！"
  },
  {
    "Id": 45,
    "Content": ""
  },
  {
    "Id": 46,
    "Content": ""
  },
  {
    "Id": 47,
    "Content": ""
  },
  {
    "Id": 48,
    "Content": ""
  },
  {
    "Id": 49,
    "Content": ""
  },
  {
    "Id": 50,
    "Content": ""
  },
  {
    "Id": 51,
    "Content": ""
  },
  {
    "Id": 52,
    "Content": ""
  },
  {
    "Id": 53,
    "Content": ""
  },
  {
    "Id": 54,
    "Content": ""
  },
  {
    "Id": 55,
    "Content": ""
  },
  {
    "Id": 56,
    "Content": ""
  },
  {
    "Id": 57,
    "Content": ""
  },
  {
    "Id": 58,
    "Content": ""
  },
  {
    "Id": 59,
    "Content": ""
  },
  {
    "Id": 60,
    "Content": ""
  },
  {
    "Id": 61,
    "Content": ""
  },
  {
    "Id": 62,
    "Content": ""
  },
  {
    "Id": 63,
    "Content": ""
  },
  {
    "Id": 64,
    "Content": ""
  },
  {
    "Id": 65,
    "Content": ""
  },
  {
    "Id": 66,
    "Content": ""
  },
  {
    "Id": 67,
    "Content": ""
  },
  {
    "Id": 68,
    "Content": ""
  },
  {
    "Id": 69,
    "Content": ""
  },
  {
    "Id": 70,
    "Content": ""
  },
  {
    "Id": 71,
    "Content": ""
  },
  {
    "Id": 72,
    "Content": ""
  },
  {
    "Id": 73,
    "Content": ""
  },
  {
    "Id": 74,
    "Content": ""
  },
  {
    "Id": 75,
    "Content": ""
  },
  {
    "Id": 76,
    "Content": ""
  },
  {
    "Id": 77,
    "Content": ""
  },
  {
    "Id": 78,
    "Content": ""
  },
  {
    "Id": 79,
    "Content": ""
  },
  {
    "Id": 80,
    "Content": ""
  },
  {
    "Id": 81,
    "Content": ""
  },
  {
    "Id": 82,
    "Content": ""
  },
  {
    "Id": 83,
    "Content": "バカな！"
  },
  {
    "Id": 84,
    "Content": ""
  },
  {
    "Id": 85,
    "Content": ""
  },
  {
    "Id": 86,
    "Content": ""
  },
  {
    "Id": 87,
    "Content": ""
  },
  {
    "Id": 88,
    "Content": ""
  },
  {
    "Id": 89,
    "Content": ""
  },
  {
    "Id": 90,
    "Content": ""
  },
  {
    "Id": 91,
    "Content": ""
  },
  {
    "Id": 92,
    "Content": ""
  },
  {
    "Id": 93,
    "Content": ""
  },
  {
    "Id": 94,
    "Content": ""
  },
  {
    "Id": 95,
    "Content": ""
  }
]
