[
    {
        "Id": 1,
        "Content": ""
    },
    {
        "Id": 2,
        "Content": "Enemy Lv. 30"
    },
    {
        "Id": 3,
        "Content": "Enemy Lv. 40"
    },
    {
        "Id": 4,
        "Content": "Enemy Lv. 50"
    },
    {
        "Id": 5,
        "Content": "Enemy Lv. 60"
    },
    {
        "Id": 6,
        "Content": "Enemy Lv. 70"
    },
    {
        "Id": 7,
        "Content": "Enemy Lv. 80"
    },
    {
        "Id": 8,
        "Content": "Enemy Lv. 90"
    },
    {
        "Id": 9,
        "Content": "Enemy Lv. 30"
    },
    {
        "Id": 10,
        "Content": "Enemy Lv. 40"
    },
    {
        "Id": 11,
        "Content": "Enemy Lv. 50"
    },
    {
        "Id": 12,
        "Content": "Enemy Lv. 60"
    },
    {
        "Id": 13,
        "Content": "Enemy Lv. 70"
    },
    {
        "Id": 14,
        "Content": "Enemy Lv. 80"
    },
    {
        "Id": 15,
        "Content": "Enemy Lv. 90"
    },
    {
        "Id": 16,
        "Content": ""
    },
    {
        "Id": 17,
        "Content": ""
    },
    {
        "Id": 18,
        "Content": ""
    },
    {
        "Id": 19,
        "Content": ""
    },
    {
        "Id": 20,
        "Content": ""
    }
]